odoo/addons/repair_quotation_manual_sync/README.rst
odoo/addons/repair_quotation_manual_sync/__init__.py
odoo/addons/repair_quotation_manual_sync/__manifest__.py
odoo/addons/repair_quotation_manual_sync/i18n/es.po
odoo/addons/repair_quotation_manual_sync/i18n/it.po
odoo/addons/repair_quotation_manual_sync/i18n/repair_quotation_manual_sync.pot
odoo/addons/repair_quotation_manual_sync/models/__init__.py
odoo/addons/repair_quotation_manual_sync/models/repair_order.py
odoo/addons/repair_quotation_manual_sync/models/sale_order.py
odoo/addons/repair_quotation_manual_sync/models/stock_move.py
odoo/addons/repair_quotation_manual_sync/readme/CONTRIBUTORS.md
odoo/addons/repair_quotation_manual_sync/readme/DESCRIPTION.md
odoo/addons/repair_quotation_manual_sync/static/description/icon.png
odoo/addons/repair_quotation_manual_sync/static/description/index.html
odoo/addons/repair_quotation_manual_sync/tests/__init__.py
odoo/addons/repair_quotation_manual_sync/tests/test_repair_quotation_manual_sync.py
odoo/addons/repair_quotation_manual_sync/views/repair_order_views.xml
odoo/addons/repair_quotation_manual_sync/views/sale_order_views.xml
odoo_addon_repair_quotation_manual_sync-17.0.1.0.1.dist-info/METADATA
odoo_addon_repair_quotation_manual_sync-17.0.1.0.1.dist-info/WHEEL
odoo_addon_repair_quotation_manual_sync-17.0.1.0.1.dist-info/top_level.txt
odoo_addon_repair_quotation_manual_sync-17.0.1.0.1.dist-info/RECORD
